dog_cli/__init__.py
dog_cli/main.py
tests/__init__.py
tests/test_cli.py
dog_cli_NXP_Sabathier-0.1.dist-info/METADATA
dog_cli_NXP_Sabathier-0.1.dist-info/WHEEL
dog_cli_NXP_Sabathier-0.1.dist-info/entry_points.txt
dog_cli_NXP_Sabathier-0.1.dist-info/top_level.txt
dog_cli_NXP_Sabathier-0.1.dist-info/RECORD
