Metadata-Version: 2.1
Name: dog-cli-NXP-Sabathier
Version: 0.1
Summary: Un CLI pour l'API dog.ceo
Home-page: https://gitlab.com/andysabathier/sabathier-cli-dogapi.git
Author: Sabathier NXP
License: UNKNOWN
Platform: UNKNOWN
Requires-Dist: click
Requires-Dist: requests
